CHANGELOG.rst
LICENSE
MANIFEST.in
README.rst
development.txt
requirements.txt
setup.cfg
setup.py
star_maker.egg-info/PKG-INFO
star_maker.egg-info/SOURCES.txt
star_maker.egg-info/dependency_links.txt
star_maker.egg-info/entry_points.txt
star_maker.egg-info/requires.txt
star_maker.egg-info/top_level.txt
starmaker/__init__.py
starmaker/cli.py
starmaker/version.py
starmaker/terraform/__init__.py
starmaker/terraform/renderer.py
starmaker/terraform/templates/__init__.py
starmaker/terraform/templates/gcp/__init__.py
starmaker/terraform/templates/gcp/main.tf.j2