Metadata-Version: 1.0
Name: star-maker
Version: 1.0.0
Summary: some tool
Home-page: UNKNOWN
Author: Gabriel Falcão
Author-email: gabriel@nacaolivre.org
License: UNKNOWN
Platform: UNKNOWN
